<?xml version='1.0' encoding='utf-8'?>
<treebank>
  <document_meta date_not_before="-299" date_not_after="-200" place_name="Alexandria"/>
  <hand_meta id="1" name="m1">
    <text_type category="Letter"/>
  </hand_meta>
  <sentence id="1">
    <word form="Ἀμύντας" head="2" lemma="Ἀμύντας" postag="n-s---mn-" relation="ATR" id="1" animacy="name"/>
    <word form="Ζήνωνι" head="3" lemma="Ζήνων" postag="n-s---md-" relation="OBJ" id="2" animacy="name"/>
    <word form="χαίρειν" head="5" lemma="χαίρω" postag="v--pna---" relation="OBJ" id="3"/>
    <word form="." head="0" lemma="." postag="u--------" relation="AuxK" id="4"/>
    <word form="[0]" head="0" lemma="" postag="" relation="PRED" id="5"/>
  </sentence>
  <sentence id="2">
    <word form="τὰ" head="3" lemma="ὁ" postag="l-p---na-" relation="ATR" id="1"/>
    <word form="μὲν" head="12" lemma="μέν" postag="d--------" relation="AuxY" id="2"/>
    <word form="Χῖα" head="4" lemma="Χῖος" postag="a-p---na-" relation="OBJ_CO" id="3"/>
    <word form="καὶ" head="13" lemma="καί" postag="b--------" relation="COORD" id="4"/>
    <word form="τὰ" head="6" lemma="ὁ" postag="l-p---na-" relation="ATR" id="5"/>
    <word form="λοιπὰ" head="4" lemma="λοιπός" postag="a-p---na-" relation="OBJ_CO" id="6"/>
    <word form="ἃ" head="8" lemma="ὅς" postag="p-p---na-" relation="OBJ" id="7"/>
    <word form="ἐνετείλω" head="6" lemma="ἐντέλλω" postag="v2saim---" relation="ATR" id="8"/>
    <word form="ἀποστεῖλαί" head="8" lemma="ἀποστέλλω" postag="v--ana---" relation="OBJ" id="9"/>
    <word form="σοι" head="9" lemma="σύ" postag="p-s---cd-" relation="OBJ" id="10"/>
    <word form="οὐκ" head="12" lemma="οὐ" postag="d--------" relation="AuxZ" id="11"/>
    <word form="ἠδυνάμεθα" head="0" lemma="δύναμαι" postag="v1paim---" relation="PRED" id="12"/>
    <word form="ἐμβαλέσθαι" head="12" lemma="ἐμβάλλω" postag="v--anm---" relation="OBJ" id="13"/>
    <word form="σοι" head="13" lemma="σύ" postag="p-s---cd-" relation="OBJ" id="14"/>
    <word form="διὰ" head="13" lemma="διά" postag="r--------" relation="AuxP" id="15"/>
    <word form="τὸ" head="19" lemma="ὁ" postag="l-s---na-" relation="ATR" id="16"/>
    <word form="τὸν" head="18" lemma="ὁ" postag="l-s---ma-" relation="ATR" id="17"/>
    <word form="βασιλέα" head="19" lemma="βασιλεύς" postag="n-s---ma-" relation="SBJ" id="18" animacy="person"/>
    <word form="μεταπέμπεσθαι" head="23" lemma="μεταπέμπω" postag="v--pne---" relation="ADV_CO" id="19"/>
    <word form="Ἀπολλώνιον" head="19" lemma="Ἀπολλώνιος" postag="n-s---ma-" relation="OBJ" id="20" animacy="name"/>
    <word form="εἰς" head="19" lemma="εἰς" postag="r--------" relation="AuxP" id="21"/>
    <word form="πόλιν" head="21" lemma="πόλις" postag="n-s---fa-" relation="OBJ" id="22" animacy="place"/>
    <word form="καὶ" head="15" lemma="καί" postag="b--------" relation="COORD" id="23"/>
    <word form="σπεύδειν" head="23" lemma="σπεύδω" postag="v--pna---" relation="ADV_CO" id="24"/>
    <word form="|gap=1||gap=2||gap=4|αι" head="0" lemma="_" postag="z--------" relation="AuxG" id="25"/>
    <word form="ἡμῖν" head="12" lemma="ἐγώ" postag="p-p---cd-" relation="ExD" id="26"/>
    <word form="τὸ" head="28" lemma="ὁ" postag="l-s---na-" relation="ATR" id="27"/>
    <word form="πλοῖον" head="24" lemma="πλοῖον" postag="n-s---na-" relation="OBJ" id="28" animacy="concrete"/>
    <word form="ἵνα" head="24" lemma="ἵνα" postag="c--------" relation="AuxC" id="29"/>
    <word form="ἔχηι" head="29" lemma="ἔχω" postag="v3spsa---" relation="ADV" id="30"/>
    <word form="τις" head="30" lemma="τις" postag="a-s---cn-" relation="SBJ" id="31"/>
    <word form="χρῆσθαι" head="30" lemma="χράω" postag="v--pne---" relation="OBJ" id="32"/>
    <word form="·" head="0" lemma="·" postag="u--------" relation="AuxK" id="33"/>
  </sentence>
  <sentence id="3">
    <word form="ὄψον" head="3" lemma="ὄψον" postag="n-s---na-" relation="OBJ" id="1" animacy="concrete"/>
    <word form="δὲ" head="3" lemma="δέ" postag="b--------" relation="AuxY" id="2"/>
    <word form="ἀπεστάλκαμεν" head="0" lemma="ἀποστέλλω" postag="v1pria---" relation="PRED" id="3"/>
    <word form="Ἀπολλωνίωι" head="1" lemma="Ἀπολλώνιος" postag="n-s---md-" relation="ATR" id="4" animacy="name"/>
    <word form="ἐν" head="3" lemma="ἐν" postag="r--------" relation="AuxP" id="5"/>
    <word form="βατανίοις" head="5" lemma="βατάνιον" orig_form="βατινίοις" postag="n-p---nd-" relation="ADV" id="6"/>
    <word form="δύο" head="8" lemma="δύο" postag="a--------" relation="ATR" id="7" is_number="true"/>
    <word form="κυβίους" head="1" lemma="κύβιον" orig_form="κυπίους" postag="n-p---na-" relation="ATR" id="8"/>
    <word form="θ" head="8" lemma="θ#" postag="a--------" relation="ATR" id="9" is_number="true"/>
    <word form="," head="0" lemma="," postag="u--------" relation="AuxX" id="10"/>
    <word form="ἐν" head="3" lemma="ἐν" postag="r--------" relation="AuxP" id="11"/>
    <word form="ἄλλοις" head="13" lemma="ἄλλος" postag="a-p---nd-" relation="ATR" id="12"/>
    <word form="βατανίοις" head="11" lemma="βατάνιον" postag="n-p---nd-" relation="ADV" id="13"/>
    <word form="δύο" head="18" lemma="δύο" postag="a--------" relation="ATR" id="14" is_number="true"/>
    <word form="σὺν" head="18" lemma="σύν" postag="r--------" relation="AuxP" id="15"/>
    <word form="τοῖς" head="13" lemma="ὁ" postag="l-p---nd-" relation="ATR" id="16"/>
    <word form="ὀπτοῖς" head="15" lemma="ὀπτός" postag="a-p---nd-" relation="ATR" id="17"/>
    <word form="φυκίδια" head="1" lemma="φυκίδιον" postag="n-p---na-" relation="APOS" id="18"/>
    <word form="η" head="18" lemma="η#" postag="a--------" relation="ATR" id="19" is_number="true"/>
    <word form="," head="0" lemma="," postag="u--------" relation="AuxX" id="20"/>
    <word form="περκία" head="18" lemma="περκίον" postag="n-p---na-" relation="CO" id="21"/>
    <word form="β" head="21" lemma="β#" postag="a--------" relation="ATR" id="22" is_number="true"/>
    <word form="," head="0" lemma="," postag="u--------" relation="AuxX" id="23"/>
    <word form="ἐν" head="28" lemma="ἐν" postag="r--------" relation="AuxP" id="24"/>
    <word form="ἄλλοις" head="26" lemma="ἄλλος" postag="a-p---nd-" relation="ATR" id="25"/>
    <word form="βατανίοις" head="24" lemma="βατάνιον" postag="n-p---nd-" relation="ATR" id="26"/>
    <word form="β" head="28" lemma="β#" postag="a--------" relation="ATR" id="27" is_number="true"/>
    <word form="κύβιοι" head="18" lemma="κύβιον" postag="n-p---n--" relation="CO" id="28"/>
    <word form="σὺν" head="28" lemma="σύν" postag="r--------" relation="AuxP" id="29"/>
    <word form="τοῖς" head="32" lemma="ὁ" postag="l-p---nd-" relation="ATR" id="30"/>
    <word form="ὀπτοῖς" head="35" lemma="ὀπτός" postag="a-p---nd-" relation="ATR" id="31"/>
    <word form="ιζ" head="29" lemma="ιζ#" postag="a--------" relation="ATR" id="32" is_number="true"/>
    <word form="," head="0" lemma="," postag="u--------" relation="AuxX" id="33"/>
    <word form="|gap=1||gap=2|ληφ|gap=1|η|gap=1|λοπα|gap=1||gap=unknown|" head="0" lemma="_" postag="z--------" relation="AuxK" id="34"/>
    <word form="[0]" head="29" lemma="" postag="" relation="ATR" id="35"/>
  </sentence>
  <sentence id="4">
    <word form="|gap=1||gap=2|ληφ|gap=1|η|gap=1|λοπα|gap=1||gap=unknown|" head="3" lemma="_" postag="z--------" relation="GAP" id="1"/>
    <word form="." head="0" lemma="." postag="u--------" relation="AuxK" id="2"/>
    <word form="[0]" head="0" lemma="" postag="" relation="PRED" id="3"/>
  </sentence>
  <sentence id="5">
    <word form="|gap=unknown_lines|" head="2" lemma="_" postag="z--------" relation="GAP" id="1"/>
    <word form="[0]" head="0" lemma="" postag="" relation="PRED" id="2"/>
  </sentence>
  <sentence id="6">
    <word form="Ζήνωνι" head="3" lemma="Ζήνων" postag="n-s---md-" relation="OBJ" id="1" animacy="name"/>
    <word form="." head="0" lemma="." postag="u--------" relation="AuxK" id="2"/>
    <word form="[0]" head="0" lemma="" postag="" relation="PRED" id="3"/>
  </sentence>
</treebank>
