<?xml version='1.0' encoding='utf-8'?>
<treebank>
  <document_meta date_not_before="201" date_not_after="299" place_name="Theadelpheia"/>
  <hand_meta id="1" name="m1">
    <text_type category="Contract"/>
  </hand_meta>
  <sentence id="1">
    <word form="ὁμολογεῖ" head="0" lemma="ὁμολογέω" orig_form="ὁμο̣λ̣ογῖ" postag="v3spia---" relation="PRED" id="1" shows-iotacism="true"/>
    <word form="Αὐρήλιος" head="1" lemma="Αὐρήλιος" postag="n-s---mn-" relation="SBJ" id="2" animacy="name"/>
    <word form="Διοσκοράμμων" head="2" lemma="Διοσκοράμμων" postag="n-s---mn-" relation="ATR" id="3" animacy="name"/>
    <word form="Σαραπίωνος" head="3" lemma="Σαραπίων" postag="n-s---mg-" relation="ATR" id="4" animacy="name"/>
    <word form="." head="0" lemma="." postag="u--------" relation="AuxK" id="5"/>
  </sentence>
  <sentence id="2">
    <word form="πέπραχα" head="16" lemma="πράσσω" postag="v1sria---" relation="PRED_CO" id="1"/>
    <word form="τῷ" head="4" lemma="ὁ" postag="l-s---md-" relation="ATR" id="2"/>
    <word form="Αὐρηλίῳ" head="4" lemma="Αὐρήλιος" postag="n-s---md-" relation="ATR" id="3" animacy="name"/>
    <word form="Σακαῶνι" head="1" lemma="Σακαῶν" postag="n-s---md-" relation="OBJ" id="4" animacy="name"/>
    <word form="ὄνον" head="1" lemma="ὄνος" postag="n-s---ma-" relation="OBJ" id="5" animacy="animal"/>
    <word form="θηλείαν" head="5" lemma="θήλειος" orig_form="θηλίαν" postag="a-s---fa-" relation="ATR" id="6" shows-iotacism="true"/>
    <word form="ἐπίλευκην" head="5" lemma="ἐπίλευκη" postag="n-s---fa-" relation="APOS" id="7"/>
    <word form="τελείαν" head="7" lemma="τέλειος" orig_form="τελίαν" postag="a-s---fa-" relation="ATR" id="8" shows-iotacism="true"/>
    <word form="ἀργυρίου" head="12" lemma="ἀργύριον" postag="n-s---ng-" relation="ATR" id="9" animacy="concrete"/>
    <word form="τῆς" head="11" lemma="ὁ" orig_form="τησδ̣εσυμ-[πε]φωνημ&lt;έ&gt;νης" postag="l-s---fg-" relation="ATR" id="10" ending-mismatch="true"/>
    <word form="τιμῆς" head="12" lemma="τιμή" postag="n-s---fg-" relation="ATR" id="11" animacy="nonconc"/>
    <word form="ταλάντων" head="7" lemma="τάλαντον" postag="n-p---ng-" relation="ATR" id="12" animacy="concrete"/>
    <word form="|gap=3|" head="0" lemma="_" postag="z--------" relation="AuxG" id="13"/>
    <word form="πλήρης" head="1" lemma="πλήρης" postag="a-s---mn-" relation="ADV" id="14"/>
    <word form="," head="0" lemma="," postag="u--------" relation="AuxX" id="15"/>
    <word form="καὶ" head="0" lemma="καί" postag="b--------" relation="COORD" id="16"/>
    <word form="ἀπέσχον" head="16" lemma="ἀπέχω" postag="v3paia---" relation="PRED_CO" id="17"/>
    <word form="τὸ" head="20" lemma="ὁ" postag="l-s---na-" relation="ATR" id="18"/>
    <word form="προκίμενον" head="20" lemma="πρόκειμαι" postag="v-sppena-" relation="ATR" id="19"/>
    <word form="ἀργύριον" head="17" lemma="ἀργύριον" postag="n-s---na-" relation="OBJ" id="20" animacy="concrete"/>
    <word form="ὡς" head="17" lemma="ὡς" postag="c--------" relation="AuxC" id="21"/>
    <word form="πρόκειται" head="21" lemma="πρόκειμαι" orig_form="πρόκιτε" postag="v3spie---" relation="ADV" id="22" shows-iotacism="true"/>
    <word form="." head="0" lemma="." postag="u--------" relation="AuxK" id="23"/>
  </sentence>
  <sentence id="3">
    <word form="αὕτη" head="3" lemma="οὗτος" postag="a-s---fn-" relation="ATR" id="1"/>
    <word form="τοιαύτη" head="5" lemma="τοιοῦτος" postag="a-s---fn-" relation="PNOM" id="2"/>
    <word form="ἀναπόρριφος" head="2" lemma="ἀναπόρριφος" orig_form="ἀνα-ποριφος" postag="a-s---fn-" relation="ATR" id="3"/>
    <word form="." head="0" lemma="." postag="u--------" relation="AuxK" id="4"/>
    <word form="[0]" head="0" lemma="" postag="" relation="PRED" id="5"/>
  </sentence>
  <sentence id="4">
    <word form="καὶ" head="3" lemma="καί" postag="b--------" relation="AuxY" id="1"/>
    <word form="ἐπερωτηθεὶς" head="3" lemma="ἐπερωτάω" orig_form="ἐπερω-τιθὶς" postag="v-sappmn-" relation="ADV" id="2" shows-iotacism="true"/>
    <word form="ὡμολόγησα" head="0" lemma="ὁμολογέω" postag="v1saia---" relation="PRED" id="3"/>
    <word form="." head="0" lemma="." postag="u--------" relation="AuxK" id="4"/>
  </sentence>
  <sentence id="5">
    <word form="ἔχειν" head="31" lemma="ἔχω" orig_form="ἐχι" postag="v--pna---" relation="OBJ" id="1" ending-mismatch="true" shows-iotacism="true"/>
    <word form="με" head="1" lemma="ἐγώ" postag="p-s---ca-" relation="SBJ" id="2"/>
    <word form="δὲ" head="1" lemma="δέ" postag="b--------" relation="AuxY" id="3"/>
    <word form="τὸν" head="5" lemma="ὁ" postag="l-s---ma-" relation="ATR" id="4"/>
    <word form="Σακαῶνα" head="1" lemma="Σακαῶν" postag="n-s---ma-" relation="SBJ" id="5" animacy="name"/>
    <word form="τὸν" head="8" lemma="ὁ" postag="l-s---ma-" relation="ATR" id="6"/>
    <word form="ταύτης" head="8" lemma="οὗτος" postag="a-s---fg-" relation="ATR" id="7"/>
    <word form="πῶλον" head="1" lemma="πῶλος" postag="n-s---ma-" relation="OBJ" id="8" animacy="animal"/>
    <word form="ἐν" head="1" lemma="ἐν" postag="r--------" relation="AuxP" id="9"/>
    <word form="παραθέσει" head="9" lemma="παράθεσις" orig_form="παραθέσι" postag="n-s---fd-" relation="ADV" id="10" animacy="nonconc" shows-iotacism="true"/>
    <word form="ἕως" head="1" lemma="ἕως" postag="r--------" relation="AuxC" id="11"/>
    <word form="ἀπογαλακτισθῇ" head="14" lemma="ἀπογαλακτίζω" postag="v3sasp---" relation="ADV_CO" id="12"/>
    <word form="," head="0" lemma="," postag="u--------" relation="AuxX" id="13"/>
    <word form="καὶ" head="11" lemma="καί" postag="b--------" relation="COORD" id="14"/>
    <word form="ἀποκαταστήσω" head="14" lemma="ἀποκαθίστημι" postag="v1sfia---" relation="ADV_CO" id="15"/>
    <word form="σοι" head="15" lemma="σύ" postag="p-s---cd-" relation="OBJ" id="16"/>
    <word form="αὐτὸν" head="15" lemma="αὐτός" postag="a-s---ma-" relation="OBJ" id="17"/>
    <word form="τοῦτο" head="19" lemma="οὗτος" postag="a-s---na-" relation="SBJ" id="18"/>
    <word form="ἐστὶν" head="15" lemma="εἰμί" postag="v3spia---" relation="OBJ" id="19"/>
    <word form="μῆνας" head="19" lemma="μείς" postag="n-p---ma-" relation="ADV" id="20" animacy="time"/>
    <word form="πέντε" head="20" lemma="πέντε" postag="a--------" relation="ATR" id="21"/>
    <word form="ἀπὸ" head="19" lemma="ἀπό" postag="r--------" relation="AuxP" id="22"/>
    <word form="τοῦ" head="25" lemma="ὁ" postag="l-s---mg-" relation="ATR" id="23"/>
    <word form="εἰσιόντος" head="25" lemma="εἰσέρχομαι" postag="v-sppamg-" relation="ATR" id="24"/>
    <word form="μηνὸς" head="22" lemma="μείς" postag="n-s---mg-" relation="ADV" id="25" animacy="time"/>
    <word form="Παῧνι" head="25" lemma="Παῦνι" postag="n-s------" relation="ATR" id="26" animacy="name"/>
    <word form="μέχρι" head="19" lemma="μέχρι" postag="r--------" relation="AuxP" id="27"/>
    <word form="μηνὸς" head="27" lemma="μείς" postag="n-s---mg-" relation="ADV" id="28" animacy="time"/>
    <word form="Ἐπίφει" head="28" lemma="Ἐπίφω" postag="v3spia---" relation="ATR" id="29"/>
    <word form="." head="0" lemma="." postag="u--------" relation="AuxK" id="30"/>
    <word form="[0]" head="0" lemma="" postag="" relation="PRED" id="31"/>
  </sentence>
  <sentence id="6">
    <word form="ἔτους" head="16" lemma="ἔτος" postag="n-s---ng-" relation="ATR" id="1" animacy="time"/>
    <word form="ιε" head="5" lemma="ιε#" postag="a--------" relation="ATR_CO" id="2" is_number="true"/>
    <word form="καὶ" head="5" lemma="καί" postag="b--------" relation="AuxY" id="3"/>
    <word form="ιδ" head="5" lemma="ιδ#" postag="a--------" relation="ATR_CO" id="4" is_number="true"/>
    <word form="καὶ" head="1" lemma="καί" postag="b--------" relation="COORD" id="5"/>
    <word form="ζ" head="5" lemma="ζ#" postag="a--------" relation="ATR_CO" id="6" is_number="true"/>
    <word form="Διοκλητιανοῦ" head="12" lemma="Διοκλητιανός" postag="n-s---mg-" relation="ATR_CO" id="7" animacy="name"/>
    <word form="καὶ" head="12" lemma="καί" postag="b--------" relation="AuxY" id="8"/>
    <word form="Μαξιμιανοῦ" head="12" lemma="Μαξιμιανός" postag="n-s---mg-" relation="ATR_CO" id="9" animacy="name"/>
    <word form="καὶ" head="12" lemma="καί" postag="b--------" relation="AuxY" id="10"/>
    <word form="Κωνσταντίου" head="12" lemma="Κωνστάντιος" orig_form="Κωστα⟦α⟧ντίου" postag="n-s---mg-" relation="ATR_CO" id="11" animacy="name"/>
    <word form="καὶ" head="6" lemma="καί" postag="b--------" relation="COORD" id="12"/>
    <word form="Μαξιμιανοῦ" head="12" lemma="Μαξιμιανός" postag="n-s---mg-" relation="ATR_CO" id="13" animacy="name"/>
    <word form="Σεβαστῶν" head="13" lemma="Σεβαστός" postag="n-p---mg-" relation="ATR" id="14" animacy="name"/>
    <word form="," head="0" lemma="," postag="u--------" relation="AuxX" id="15"/>
    <word form="Παῧνι" head="19" lemma="Παυνις" postag="n-s---mv-" relation="ADV" id="16" animacy="name"/>
    <word form="ιζ" head="16" lemma="ιζ#" postag="a--------" relation="ATR" id="17" is_number="true"/>
    <word form="." head="0" lemma="." postag="u--------" relation="AuxK" id="18"/>
    <word form="[0]" head="0" lemma="" postag="" relation="PRED" id="19"/>
  </sentence>
  <sentence id="7">
    <word form="Αὐρήλιος" head="3" lemma="Αὐρήλιος" postag="n-s---mn-" relation="SBJ" id="1" animacy="name"/>
    <word form="Διοσκοράμμων" head="1" lemma="Διοσκοράμμων" postag="n-s---mn-" relation="ATR" id="2" animacy="name"/>
    <word form="ἔγραψα" head="0" lemma="γράφω" postag="v1saia---" relation="PRED" id="3"/>
    <word form="τὰ" head="5" lemma="ὁ" postag="l-p---na-" relation="ATR" id="4"/>
    <word form="ὅλα" head="3" lemma="ὅλος" postag="a-p---na-" relation="OBJ" id="5"/>
    <word form="." head="0" lemma="." postag="u--------" relation="AuxK" id="6"/>
  </sentence>
</treebank>
